optimizelab/Instance_10.xlsx
optimizelab/__init__.py
optimizelab/ant_colony.py
optimizelab/binary_ga.py
optimizelab/continuous_ga.py
optimizelab/gray_wolf.py
optimizelab/particle_swarm.py
optimizelab/shuffled_frog.py
optimizelab/simulated_annealing.py
optimizelab/tabu_search.py
optimizelab/tsp_genetic.py
optimizelab-0.1.2.dist-info/licenses/LICENSE
optimizelab-0.1.2.dist-info/METADATA
optimizelab-0.1.2.dist-info/WHEEL
optimizelab-0.1.2.dist-info/top_level.txt
optimizelab-0.1.2.dist-info/RECORD
