Metadata-Version: 2.4
Name: optimizelab
Version: 0.1.2
Summary: A collection of classical and nature-inspired optimization algorithms implemented in Python.
Author: code spaze
Requires-Python: >=3.8
License-File: LICENSE
Requires-Dist: numpy
Requires-Dist: matplotlib
Requires-Dist: networkx
Requires-Dist: pandas
Requires-Dist: openpyxl
Dynamic: author
Dynamic: license-file
Dynamic: requires-dist
Dynamic: requires-python
Dynamic: summary
